gdbundle/__init__.py
gdbundle/commands_gdb.py
gdbundle/commands_lldb.py
gdbundle-0.0.4.dist-info/LICENSE
gdbundle-0.0.4.dist-info/WHEEL
gdbundle-0.0.4.dist-info/METADATA
gdbundle-0.0.4.dist-info/RECORD
